PythonZhilv/README.md
PythonZhilv/__init__.py
PythonZhilv/__main__.py
PythonZhilv/file.epub
PythonZhilv/index.html
PythonZhilv/css/__init__.py
PythonZhilv/css/annotations.css
PythonZhilv/css/main.css
PythonZhilv/css/normalize.css
PythonZhilv/css/popup.css
PythonZhilv/font/__init__.py
PythonZhilv/font/fontello.eot
PythonZhilv/font/fontello.svg
PythonZhilv/font/fontello.ttf
PythonZhilv/font/fontello.woff
PythonZhilv/img/__init__.py
PythonZhilv/img/annotator-glyph-sprite.png
PythonZhilv/img/annotator-icon-sprite.png
PythonZhilv/img/apple-touch-icon.png
PythonZhilv/img/cancelfullscreen.png
PythonZhilv/img/close.png
PythonZhilv/img/fullscreen.png
PythonZhilv/img/loader.gif
PythonZhilv/img/menu-icon.png
PythonZhilv/img/save.png
PythonZhilv/img/saved.png
PythonZhilv/img/settings-s.png
PythonZhilv/img/settings.png
PythonZhilv/img/star.png
PythonZhilv/js/__init__.py
PythonZhilv/js/epub.js
PythonZhilv/js/epub.min.js
PythonZhilv/js/epub.min.map
PythonZhilv/js/hooks.min.js
PythonZhilv/js/hooks.min.map
PythonZhilv/js/reader.js
PythonZhilv/js/reader.js.map
PythonZhilv/js/reader.min.js
PythonZhilv/js/reader.min.map
PythonZhilv/js/hooks/__init__.py
PythonZhilv/js/hooks/extensions/__init__.py
PythonZhilv/js/hooks/extensions/highlight.js
PythonZhilv/js/libs/__init__.py
PythonZhilv/js/libs/jquery.min.js
PythonZhilv/js/libs/localforage.min.js
PythonZhilv/js/libs/screenfull.js
PythonZhilv/js/libs/screenfull.min.js
PythonZhilv/js/libs/zip.min.js
PythonZhilv/js/plugins/__init__.py
PythonZhilv/js/plugins/hypothesis.js
PythonZhilv/js/plugins/search.js
python_zhilv-2024.3.2.0.dist-info/METADATA
python_zhilv-2024.3.2.0.dist-info/WHEEL
python_zhilv-2024.3.2.0.dist-info/entry_points.txt
python_zhilv-2024.3.2.0.dist-info/top_level.txt
python_zhilv-2024.3.2.0.dist-info/RECORD
